pynamics/__init__.py
pynamics/_simulator.py
pynamics/simulations.py
pynamics/_noise/__init__.py
pynamics/_noise/_noise_generators.py
pynamics/_solvers/__init__.py
pynamics/_solvers/_solver.py
pynamics/_solvers/_fixed_step/__init__.py
pynamics/_solvers/_fixed_step/_fixed_step_solver.py
pynamics/_solvers/_fixed_step/_fixed_step_solvers.py
pynamics/_solvers/_variable_step/__init__.py
pynamics/_solvers/_variable_step/_variable_step_solver.py
pynamics/_solvers/_variable_step/_variable_step_solvers.py
pynamics/controllers/__init__.py
pynamics/controllers/base.py
pynamics/controllers/dummy.py
pynamics/models/__init__.py
pynamics/models/base.py
pynamics/models/model_conversion.py
pynamics/models/state_space_models.py
pynamics2-1.0.0.dist-info/LICENSE
pynamics2-1.0.0.dist-info/METADATA
pynamics2-1.0.0.dist-info/WHEEL
pynamics2-1.0.0.dist-info/top_level.txt
pynamics2-1.0.0.dist-info/RECORD
