Metadata-Version: 2.1
Name: pynamics2
Version: 1.0.0
Summary: Physical modelling tools for advanced control design.
Author-email: Miguel Santos Loureiro <miguel.santos.loureiro@gmail.com>
License: Apache License
Project-URL: repository, https://github.com/MiguelLoureiro98/pynamics
Project-URL: docs, https://miguelloureiro98.github.io/pynamics/
Keywords: physical-models,dynamical-systems,simulations
Classifier: Programming Language :: Python :: 3
Classifier: License :: OSI Approved :: Apache Software License
Classifier: Natural Language :: English
Classifier: Operating System :: OS Independent
Classifier: Topic :: Software Development :: Libraries :: Python Modules
Classifier: Topic :: Scientific/Engineering
Classifier: Intended Audience :: Science/Research
Classifier: Intended Audience :: Developers
Classifier: Intended Audience :: Education
License-File: LICENSE
Requires-Dist: numpy >=1.26.3
Requires-Dist: pandas >=2.1.4
Requires-Dist: matplotlib >=3.9.2
Requires-Dist: control >=0.10.1
Provides-Extra: dev
Requires-Dist: build >=1.2.1 ; extra == 'dev'
Requires-Dist: twine >=5.1.1 ; extra == 'dev'
Requires-Dist: mkdocs >=1.6.0 ; extra == 'dev'
Requires-Dist: mkdocs-material >=9.5.30 ; extra == 'dev'
Requires-Dist: mkdocstrings-python >=1.11.1 ; extra == 'dev'
Requires-Dist: pymdown-extensions >=10.9 ; extra == 'dev'
